bpchildren/__init__.py
bpchildren/__main__.py
bpchildren-0.2.0.dist-info/METADATA
bpchildren-0.2.0.dist-info/WHEEL
bpchildren-0.2.0.dist-info/entry_points.txt
bpchildren-0.2.0.dist-info/top_level.txt
bpchildren-0.2.0.dist-info/RECORD
