Metadata-Version: 2.4
Name: bpchildren
Version: 0.2.0
Summary: MCP server for BP percentile calculation
Author-email: Hyung-Chul Lee <vital@snu.ac.kr>
License-Expression: MIT
Requires-Python: >=3.12
Requires-Dist: scipy
Requires-Dist: mcp
